odoo8_addon_sale_order_import_ubl-8.0.1.0.0.99.dev6-nspkg.pth
odoo_addons/sale_order_import_ubl/README.rst
odoo_addons/sale_order_import_ubl/__init__.py
odoo_addons/sale_order_import_ubl/__openerp__.py
odoo_addons/sale_order_import_ubl/demo/demo_data.xml
odoo_addons/sale_order_import_ubl/i18n/sale_order_import_ubl.pot
odoo_addons/sale_order_import_ubl/static/description/icon.png
odoo_addons/sale_order_import_ubl/tests/__init__.py
odoo_addons/sale_order_import_ubl/tests/test_ubl_order_import.py
odoo_addons/sale_order_import_ubl/tests/files/UBL-Order-2.0-Example.xml
odoo_addons/sale_order_import_ubl/tests/files/UBL-Order-2.1-Example.xml
odoo_addons/sale_order_import_ubl/tests/files/UBL-RequestForQuotation-2.0-Example.xml
odoo_addons/sale_order_import_ubl/tests/files/UBL-RequestForQuotation-2.1-Example.xml
odoo_addons/sale_order_import_ubl/wizard/__init__.py
odoo_addons/sale_order_import_ubl/wizard/sale_order_import.py
odoo8_addon_sale_order_import_ubl-8.0.1.0.0.99.dev6.dist-info/METADATA
odoo8_addon_sale_order_import_ubl-8.0.1.0.0.99.dev6.dist-info/WHEEL
odoo8_addon_sale_order_import_ubl-8.0.1.0.0.99.dev6.dist-info/namespace_packages.txt
odoo8_addon_sale_order_import_ubl-8.0.1.0.0.99.dev6.dist-info/top_level.txt
odoo8_addon_sale_order_import_ubl-8.0.1.0.0.99.dev6.dist-info/RECORD
